nusquids.libs/libgsl-f7298b36.so.23.1.0
nusquids.libs/libgslcblas-cf1da87e.so.0.0.0
nusquids.libs/libnuSQuIDS-6278a222.so
nusquids.libs/libhdf5-463e48d5.so.103.1.0
nusquids.libs/libsz-81b556a2.so.2.0.1
nusquids.libs/libSQuIDS-a816da95.so
nusquids.libs/libaec-34bb4966.so.0.0.8
nusquids.libs/libhdf5_hl-74316838.so.100.1.2
lib/libnuSQuIDS.so
lib/libnuSQuIDS.so.1
lib/libnuSQuIDS.so.1.13.3
lib/libSQuIDS.so.1.3.1
lib/libSQuIDS.so.1
lib/libnuSQuIDS.a
lib/libSQuIDS.a
lib/libSQuIDS.so
lib/nuSQuIDS.so
lib/pkgconfig/nusquids.pc
lib/pkgconfig/hdf5.pc
nusquids-1.13.3.dist-info/WHEEL
nusquids-1.13.3.dist-info/METADATA
nusquids-1.13.3.dist-info/RECORD
nusquids-1.13.3.dist-info/licenses/LICENSE
nusquids-1.13.3.dist-info/licenses/AUTHORS
nuSQuIDS/nuSQUIDSTools.py
nuSQuIDS/libSQuIDS.so.1.3.1
nuSQuIDS/libSQuIDS.so.1
nuSQuIDS/libSQuIDS.a
nuSQuIDS/libSQuIDS.so
nuSQuIDS/__init__.py
nuSQuIDS/nuSQuIDS.so
bin/nusquids-config
include/nuSQuIDS/marray.h
include/nuSQuIDS/taudecay.h
include/nuSQuIDS/resources.h
include/nuSQuIDS/ThreadPool.h
include/nuSQuIDS/nuSQuIDS.h
include/nuSQuIDS/body.h
include/nuSQuIDS/tools.h
include/nuSQuIDS/aligned_alloc.h
include/nuSQuIDS/version.h
include/nuSQuIDS/xsections.h
include/nuSQuIDS/AdaptiveQuad.h
