Metadata-Version: 2.2
Name: nuSQuIDS
Version: 1.13.3
Summary: Neutrino propagation library with pybind11 bindings for reference see
Author-Email: =?utf-8?q?Carlos_A=2E_Arg=C3=BCelles_Delgado?= <carguelles@fas.harvard.edu>
License: GNU LESSER GENERAL PUBLIC LICENSE
Classifier: Programming Language :: Python :: 3
Classifier: Programming Language :: C++
Classifier: License :: OSI Approved :: MIT License
Requires-Python: >=3.8
Requires-Dist: numpy
Provides-Extra: plot
Requires-Dist: matplotlib; extra == "plot"
